git_workflow_test/__init__.py
git_workflow_test/app.py
git_workflow_test/config.py
git_workflow_test-1.0.0.dist-info/METADATA
git_workflow_test-1.0.0.dist-info/WHEEL
git_workflow_test-1.0.0.dist-info/RECORD
